intentkit/.dockerignore
intentkit/LICENSE
intentkit/MANIFEST.in
intentkit/README.md
intentkit/__init__.py
intentkit/abstracts/__init__.py
intentkit/abstracts/agent.py
intentkit/abstracts/api.py
intentkit/abstracts/engine.py
intentkit/abstracts/graph.py
intentkit/abstracts/skill.py
intentkit/abstracts/twitter.py
intentkit/abstracts/wallet.py
intentkit/clients/__init__.py
intentkit/clients/cdp.py
intentkit/clients/evm_wallet.py
intentkit/clients/privy.py
intentkit/clients/s3.py
intentkit/clients/signer.py
intentkit/clients/twitter.py
intentkit/clients/web3.py
intentkit/config/__init__.py
intentkit/config/base.py
intentkit/config/config.py
intentkit/config/db.py
intentkit/config/db_mig.py
intentkit/config/redis.py
intentkit/core/__init__.py
intentkit/core/account_checking.py
intentkit/core/agent.py
intentkit/core/agent_activity.py
intentkit/core/agent_post.py
intentkit/core/api.py
intentkit/core/asset.py
intentkit/core/budget.py
intentkit/core/chat.py
intentkit/core/cleanup.py
intentkit/core/client.py
intentkit/core/credit.py
intentkit/core/draft.py
intentkit/core/draft_chat.py
intentkit/core/engine.py
intentkit/core/middleware.py
intentkit/core/prompt.py
intentkit/core/scheduler.py
intentkit/core/statistics.py
intentkit/core/template.py
intentkit/core/user.py
intentkit/core/manager/__init__.py
intentkit/core/manager/engine.py
intentkit/core/manager/service.py
intentkit/core/manager/skills.py
intentkit/core/system_skills/__init__.py
intentkit/core/system_skills/call_agent.py
intentkit/core/system_skills/create_activity.py
intentkit/core/system_skills/create_post.py
intentkit/core/system_skills/recent_activities.py
intentkit/models/__init__.py
intentkit/models/agent.py
intentkit/models/agent_activity.py
intentkit/models/agent_data.py
intentkit/models/agent_post.py
intentkit/models/agent_public.json
intentkit/models/agent_schema.json
intentkit/models/app_setting.py
intentkit/models/base.py
intentkit/models/chat.py
intentkit/models/credit.py
intentkit/models/db.py
intentkit-0.9.22.dist-info/METADATA
intentkit-0.9.22.dist-info/WHEEL
intentkit-0.9.22.dist-info/licenses/LICENSE
intentkit-0.9.22.dist-info/RECORD
