Metadata-Version: 2.4
Name: intentkit
Version: 0.9.22
Summary: Intent-based AI Agent Platform - Core Package
Project-URL: Homepage, https://github.com/crestalnetwork/intentkit
Project-URL: Repository, https://github.com/crestalnetwork/intentkit
Project-URL: Documentation, https://github.com/crestalnetwork/intentkit/tree/main/docs
Project-URL: Bug Tracker, https://github.com/crestalnetwork/intentkit/issues
Author-email: Ruihua <ruihua@crestal.network>
License: MIT License
License-File: LICENSE
Keywords: agent,ai,blockchain,crypto,intent
Classifier: Development Status :: 4 - Beta
Classifier: Intended Audience :: Developers
Classifier: License :: OSI Approved :: MIT License
Classifier: Programming Language :: Python :: 3
Classifier: Programming Language :: Python :: 3.13
Classifier: Topic :: Scientific/Engineering :: Artificial Intelligence
Classifier: Topic :: Software Development :: Libraries :: Python Modules
Requires-Python: ==3.13.*
Requires-Dist: aiohttp>=3.11.16
Requires-Dist: aiosqlite>=0.21.0
Requires-Dist: asyncpg>=0.30.0
Requires-Dist: aws-secretsmanager-caching>=1.1.3
Requires-Dist: boto3<2.0.0,>=1.37.23
Requires-Dist: botocore>=1.35.97
Requires-Dist: cdp-sdk>=1.31.1
Requires-Dist: cron-validator<2.0.0,>=1.0.8
Requires-Dist: epyxid>=0.3.3
Requires-Dist: eth-abi>=5.0.0
Requires-Dist: eth-keys>=0.4.0
Requires-Dist: eth-utils>=2.1.0
Requires-Dist: fastapi>=0.115.8
Requires-Dist: filetype<2.0.0,>=1.2.0
Requires-Dist: httpx>=0.28.1
Requires-Dist: jsonref>=1.1.0
Requires-Dist: langchain-community>=0.3.19
Requires-Dist: langchain-core>=0.3.43
Requires-Dist: langchain-deepseek>=0.1.4
Requires-Dist: langchain-google-genai>=3.2.0
Requires-Dist: langchain-openai>=0.3.8
Requires-Dist: langchain-text-splitters>=0.3.8
Requires-Dist: langchain-xai>=0.2.1
Requires-Dist: langchain>=0.3.25
Requires-Dist: langgraph-checkpoint-postgres>=2.0.16
Requires-Dist: langgraph-checkpoint>=2.0.18
Requires-Dist: langgraph-prebuilt>=0.6.1
Requires-Dist: langgraph>=0.6.1
Requires-Dist: mypy-boto3-s3<2.0.0,>=1.37.24
Requires-Dist: openai>=1.59.6
Requires-Dist: pillow<13.0.0,>=11.1.0
Requires-Dist: psycopg-pool>=3.2.4
Requires-Dist: psycopg>=3.2.9
Requires-Dist: pydantic>=2.10.6
Requires-Dist: python-dotenv>=1.0.1
Requires-Dist: pytz>=2025.1
Requires-Dist: pyyaml>=6.0.2
Requires-Dist: redis<8.0.0,>=5.2.1
Requires-Dist: requests-oauthlib>=2.0.0
Requires-Dist: requests>=2.32.3
Requires-Dist: slack-sdk>=3.34.0
Requires-Dist: sqlalchemy[asyncio]>=2.0.37
Requires-Dist: starlette>=0.47.1
Requires-Dist: supabase>=2.16.0
Requires-Dist: tenacity>=9.1.2
Requires-Dist: tweepy[async]>=4.15.0
Requires-Dist: uvicorn<1.0.0,>=0.34.0
Requires-Dist: web3>=7.10.0
Requires-Dist: x402>=2.0.0
